legion_utils/.DS_Store
legion_utils/__init__.py
legion_utils/alerter.py
legion_utils/cli/__init__.py
legion_utils/cli/cli.py
legion_utils/cli/utils.py
legion_utils/core.py
legion_utils/instrumentation.py
legion_utils/princeps/__init__.py
legion_utils/princeps/config.py
legion_utils/princeps/princeps.py
legion_utils/py.typed
legion_utils-0.6.5.dist-info/entry_points.txt
legion_utils-0.6.5.dist-info/WHEEL
legion_utils-0.6.5.dist-info/METADATA
legion_utils-0.6.5.dist-info/licenses/LICENSE
legion_utils-0.6.5.dist-info/RECORD
