Metadata-Version: 2.1
Name: legion-utils
Version: 0.6.5
Summary: Utilities for Legion Reporters and Monitors
License: GPL-3.0-or-later
Author-email: Eugene Kovalev <eugene@kovalev.systems>
Requires-Python: >3.9.0,<4.0
Requires-Dist: beartype>=0.19.0
Requires-Dist: click>=8.1.7
Requires-Dist: environs>=14.1.1
Requires-Dist: psutil>=5.9.6
Requires-Dist: robotnikmq>=0.7.6
Requires-Dist: schedule>=1.2.2
Requires-Dist: sqlitedict>=2.1.0
